LICENSE.txt
public_test/__init__.py
public_test-0.1.0.dist-info/LICENSE.txt
public_test-0.1.0.dist-info/WHEEL
public_test-0.1.0.dist-info/METADATA
public_test-0.1.0.dist-info/RECORD
