Metadata-Version: 2.1
Name: public-test
Version: 0.1.0
Summary: Sample public project setup
Home-page: https://github.com/digismoothie/public-test
License: MIT
Author: Digismoothie s.r.o.
Author-email: info@digismoothie.com
Requires-Python: >=3.8,<4.0
Classifier: License :: OSI Approved :: MIT License
Classifier: Programming Language :: Python :: 3
Classifier: Programming Language :: Python :: 3.8
Classifier: Programming Language :: Python :: 3.9
Project-URL: Repository, https://github.com/digismoothie/public-test
